powerprofile/__init__.py
powerprofile/exceptions.py
powerprofile/powerprofile.py
powerprofile/utils.py
powerprofile-0.31.0.dist-info/licenses/LICENSE
spec/exceptions_spec.py
spec/interpolate_spec.py
spec/powerprofile_spec.py
spec/powerprofileqh_spec.py
powerprofile-0.31.0.dist-info/METADATA
powerprofile-0.31.0.dist-info/WHEEL
powerprofile-0.31.0.dist-info/top_level.txt
powerprofile-0.31.0.dist-info/RECORD
