Metadata-Version: 2.4
Name: powerprofile
Version: 0.31.0
Summary: Library to manage power profiles
Home-page: https://github.com/gisce/powerprofile
Author: GISCE-TI, S.L.
Author-email: "GISCE-TI, S.L." <devel@gisce.net>
License-Expression: AGPL-3.0-only
Project-URL: Homepage, https://github.com/gisce/powerprofile
Classifier: Development Status :: 4 - Beta
Classifier: Programming Language :: Python :: 2.7
Classifier: Programming Language :: Python :: 3.11
Classifier: Topic :: Utilities
Requires-Python: >=2.7
License-File: LICENSE
Dynamic: author
Dynamic: home-page
Dynamic: license-file
